airflow/providers/nomad/LICENSE
airflow/providers/nomad/__init__.py
airflow/providers/nomad/constants.py
airflow/providers/nomad/exceptions.py
airflow/providers/nomad/get_provider_info.py
airflow/providers/nomad/log.py
airflow/providers/nomad/manager.py
airflow/providers/nomad/models.py
airflow/providers/nomad/utils.py
airflow/providers/nomad/decorators/__init__.py
airflow/providers/nomad/decorators/job.py
airflow/providers/nomad/decorators/python.py
airflow/providers/nomad/decorators/task.py
airflow/providers/nomad/docker/Dockerfile-extras.runner
airflow/providers/nomad/docker/Dockerfile.runner
airflow/providers/nomad/docker/build.sh
airflow/providers/nomad/executors/__init__.py
airflow/providers/nomad/executors/nomad_executor.py
airflow/providers/nomad/generic_interfaces/__init__.py
airflow/providers/nomad/generic_interfaces/executor_interface.py
airflow/providers/nomad/generic_interfaces/executor_log_handlers.py
airflow/providers/nomad/generic_interfaces/nomad_operator_interface.py
airflow/providers/nomad/operators/__init__.py
airflow/providers/nomad/operators/job.py
airflow/providers/nomad/operators/python.py
airflow/providers/nomad/operators/task.py
airflow/providers/nomad/templates/airflow.cfg
airflow/providers/nomad/templates/job_template.py
apache_airflow_providers_nomad-0.0.7.dist-info/entry_points.txt
apache_airflow_providers_nomad-0.0.7.dist-info/licenses/LICENSE
apache_airflow_providers_nomad-0.0.7.dist-info/WHEEL
apache_airflow_providers_nomad-0.0.7.dist-info/METADATA
apache_airflow_providers_nomad-0.0.7.dist-info/RECORD
