Metadata-Version: 2.4
Name: apache-airflow-providers-nomad
Version: 0.0.7
Summary: Provider package for Nomad (executor, operators, etc.) for Apache Airflow
Keywords: airflow-provider,nomad,airflow,integration
Author-email: Judit Novak <judit.novak@gmail.com>
Maintainer-email: Judit Novak <judit.novak@gmail.com>
Requires-Python: >=3.10
Classifier: Development Status :: 4 - Beta
Classifier: Environment :: Console
Classifier: Environment :: Web Environment
Classifier: Intended Audience :: Developers
Classifier: Intended Audience :: System Administrators
Classifier: Framework :: Apache Airflow
Classifier: Framework :: Apache Airflow :: Provider
Classifier: License :: OSI Approved :: Apache Software License
Classifier: Programming Language :: Python :: 3.10
Classifier: Programming Language :: Python :: 3.11
Classifier: Programming Language :: Python :: 3.12
Classifier: Programming Language :: Python :: 3.13
Classifier: Topic :: System :: Monitoring
License-File: LICENSE
Requires-Dist: apache-airflow-core >=3.0.4
Requires-Dist: apache-airflow-task-sdk
Requires-Dist: flask>=3.1.2
Requires-Dist: jq>=1.10.0
Requires-Dist: pydantic>=2.12
Requires-Dist: python-nomad>=2.1.0
Requires-Dist: requests>=2.32.5
Requires-Dist: tenacity>=9.1.2
Requires-Dist: apache-airflow-providers-nomad ; extra == "prelease"
Provides-Extra: prelease
